{
	"name": "web activity",
	"properties": {
		"activities": [
			{
				"name": "Switch1",
				"type": "Switch",
				"dependsOn": [],
				"userProperties": [],
				"typeProperties": {
					"on": {
						"value": "@pipeline().parameters.foldername",
						"type": "Expression"
					},
					"cases": [
						{
							"value": "output1",
							"activities": [
								{
									"name": "Copy data1",
									"type": "Copy",
									"dependsOn": [],
									"policy": {
										"timeout": "0.12:00:00",
										"retry": 0,
										"retryIntervalInSeconds": 30,
										"secureOutput": false,
										"secureInput": false
									},
									"userProperties": [],
									"typeProperties": {
										"source": {
											"type": "BinarySource",
											"storeSettings": {
												"type": "AzureBlobStorageReadSettings",
												"recursive": true
											},
											"formatSettings": {
												"type": "BinaryReadSettings"
											}
										},
										"sink": {
											"type": "BinarySink",
											"storeSettings": {
												"type": "AzureBlobStorageWriteSettings"
											}
										},
										"enableStaging": false
									},
									"inputs": [
										{
											"referenceName": "ds_input",
											"type": "DatasetReference"
										}
									],
									"outputs": [
										{
											"referenceName": "ds_output",
											"type": "DatasetReference",
											"parameters": {
												"foldername": {
													"value": "@pipeline().parameters.foldername",
													"type": "Expression"
												}
											}
										}
									]
								}
							]
						},
						{
							"value": "output2",
							"activities": [
								{
									"name": "Copy data2",
									"type": "Copy",
									"dependsOn": [],
									"policy": {
										"timeout": "0.12:00:00",
										"retry": 0,
										"retryIntervalInSeconds": 30,
										"secureOutput": false,
										"secureInput": false
									},
									"userProperties": [],
									"typeProperties": {
										"source": {
											"type": "BinarySource",
											"storeSettings": {
												"type": "AzureBlobStorageReadSettings",
												"recursive": true
											},
											"formatSettings": {
												"type": "BinaryReadSettings"
											}
										},
										"sink": {
											"type": "BinarySink",
											"storeSettings": {
												"type": "AzureBlobStorageWriteSettings"
											}
										},
										"enableStaging": false
									},
									"inputs": [
										{
											"referenceName": "ds_input",
											"type": "DatasetReference"
										}
									],
									"outputs": [
										{
											"referenceName": "ds_output",
											"type": "DatasetReference",
											"parameters": {
												"foldername": {
													"value": "@pipeline().parameters.foldername",
													"type": "Expression"
												}
											}
										}
									]
								}
							]
						},
						{
							"value": "output3",
							"activities": [
								{
									"name": "Copy data4",
									"type": "Copy",
									"dependsOn": [],
									"policy": {
										"timeout": "0.12:00:00",
										"retry": 0,
										"retryIntervalInSeconds": 30,
										"secureOutput": false,
										"secureInput": false
									},
									"userProperties": [],
									"typeProperties": {
										"source": {
											"type": "BinarySource",
											"storeSettings": {
												"type": "AzureBlobStorageReadSettings",
												"recursive": true
											},
											"formatSettings": {
												"type": "BinaryReadSettings"
											}
										},
										"sink": {
											"type": "BinarySink",
											"storeSettings": {
												"type": "AzureBlobStorageWriteSettings"
											}
										},
										"enableStaging": false
									},
									"inputs": [
										{
											"referenceName": "ds_input",
											"type": "DatasetReference"
										}
									],
									"outputs": [
										{
											"referenceName": "ds_output",
											"type": "DatasetReference",
											"parameters": {
												"foldername": {
													"value": "@pipeline().parameters.foldername",
													"type": "Expression"
												}
											}
										}
									]
								}
							]
						}
					],
					"defaultActivities": [
						{
							"name": "Copy data3",
							"type": "Copy",
							"dependsOn": [],
							"policy": {
								"timeout": "0.12:00:00",
								"retry": 0,
								"retryIntervalInSeconds": 30,
								"secureOutput": false,
								"secureInput": false
							},
							"userProperties": [],
							"typeProperties": {
								"source": {
									"type": "BinarySource",
									"storeSettings": {
										"type": "AzureBlobStorageReadSettings",
										"recursive": true
									},
									"formatSettings": {
										"type": "BinaryReadSettings"
									}
								},
								"sink": {
									"type": "BinarySink",
									"storeSettings": {
										"type": "AzureBlobStorageWriteSettings"
									}
								},
								"enableStaging": false
							},
							"inputs": [
								{
									"referenceName": "ds_input",
									"type": "DatasetReference"
								}
							],
							"outputs": [
								{
									"referenceName": "ds_output",
									"type": "DatasetReference",
									"parameters": {
										"foldername": {
											"value": "@pipeline().parameters.foldername",
											"type": "Expression"
										}
									}
								}
							]
						}
					]
				}
			}
		],
		"parameters": {
			"foldername": {
				"type": "string"
			}
		},
		"annotations": [],
		"lastPublishTime": "2024-05-21T13:52:18Z"
	},
	"type": "Microsoft.DataFactory/factories/pipelines"
}